{
	"$schema": "http://json-schema.org/draft-07/schema#",
	"properties": {
		"machineSettings": {
			"additionalProperties": {
				"properties": {
					"setupStepSettings": {
						"additionalProperties": false,
						"patternProperties": {
							"^[0-9]+$": {
								"properties": {
									"done": {
										"type": "boolean"
									},
									"setupStepTaskSettings": {
										"additionalProperties": false,
										"patternProperties": {
											"^[0-9]+$": {
												"properties": {
													"done": {
														"type": "boolean"
													},
													"skipped": {
														"type": "boolean"
													}
												},
												"type": "object"
											}
										},
										"type": "object"
									},
									"skipped": {
										"type": "boolean"
									}
								},
								"type": "object"
							}
						},
						"type": "object"
					}
				},
				"type": "object"
			},
			"type": "object"
		}
	},
	"type": "object"
}
